LICENSE
MANIFEST.in
README.md
README.rst
setup.cfg
setup.py
django_privacyidea_auth/__init__.py
django_privacyidea_auth/privacyidea_auth.py
django_privacyidea_auth.egg-info/PKG-INFO
django_privacyidea_auth.egg-info/SOURCES.txt
django_privacyidea_auth.egg-info/dependency_links.txt
django_privacyidea_auth.egg-info/requires.txt
django_privacyidea_auth.egg-info/top_level.txt