Metadata-Version: 1.1
Name: django-privacyidea-auth
Version: 0.3
Summary: Authenticate against a privacyIDEA server. (https://www.privacyidea.org/)
Home-page: https://www.tek2b.de/
Author: Jens Weber
Author-email: jweber@tek2b.de
License: BSD License
Platform: UNKNOWN
Classifier: Development Status :: 5 - Production/Stable
Classifier: Environment :: Web Environment
Classifier: Framework :: Django
Classifier: Intended Audience :: Developers
Classifier: License :: OSI Approved :: BSD License
Classifier: Operating System :: OS Independent
Classifier: Programming Language :: Python
Classifier: Programming Language :: Python :: 2.7
Classifier: Programming Language :: Python :: 3.0
Classifier: Topic :: Internet
Classifier: Topic :: Security
Classifier: Topic :: System :: Systems Administration :: Authentication/Directory
Classifier: Topic :: Software Development :: Libraries
